LICENSE
MANIFEST.in
README.rst
setup.py
django_procmail.egg-info/PKG-INFO
django_procmail.egg-info/SOURCES.txt
django_procmail.egg-info/dependency_links.txt
django_procmail.egg-info/not-zip-safe
django_procmail.egg-info/requires.txt
django_procmail.egg-info/top_level.txt
procmail/__init__.py
procmail/admin.py
procmail/config.py
procmail/exceptions.py
procmail/forms.py
procmail/forms_initial.py
procmail/forms_utils.py
procmail/models.py
procmail/tests.py
procmail/urls.py
procmail/utils.py
procmail/views.py
procmail/locale/fr/LC_MESSAGES/django.mo
procmail/locale/fr/LC_MESSAGES/django.po
procmail/migrations/__init__.py
procmail/static/procmail/functions.js
procmail/static/procmail/list.js
procmail/static/procmail/styles.css
procmail/static/procmail/tree.css
procmail/templates/procmail/base.html
procmail/templates/procmail/create.html
procmail/templates/procmail/delete.html
procmail/templates/procmail/edit.html
procmail/templates/procmail/edit_simple.html
procmail/templates/procmail/form.html
procmail/templates/procmail/form_javascript.html
procmail/templates/procmail/index.html
procmail/templates/procmail/javascript.html
procmail/templates/procmail/list.html
procmail/templates/procmail/parse_error.html