Metadata-Version: 1.1
Name: django-procmail
Version: 0.1
Summary: A web interface for editing procmail's procmailrc files.
Home-page: https://github.com/nitmir/django-procmail
Author: Valentin Samir
Author-email: valentin.samir@crans.org
License: GPLv3
Download-URL: https://github.com/nitmir/django-procmail/releases
Keywords: django,procmail,mail,filter,gui,web,interface
Platform: UNKNOWN
Classifier: Environment :: Web Environment
Classifier: Framework :: Django
Classifier: Intended Audience :: Developers
Classifier: License :: OSI Approved :: GNU General Public License v3 (GPLv3)
Classifier: Operating System :: OS Independent
Classifier: Programming Language :: Python
Classifier: Programming Language :: Python :: 2
Classifier: Topic :: Internet :: WWW/HTTP
Classifier: Topic :: Internet :: WWW/HTTP :: Dynamic Content
